qibotf-0.0.6.dist-info/LICENSE
qibotf-0.0.6.dist-info/METADATA
qibotf-0.0.6.dist-info/top_level.txt
qibotf-0.0.6.dist-info/RECORD
qibotf-0.0.6.dist-info/WHEEL
qibotf/__init__.py
qibotf/tests/test_gates.py
qibotf/tests/test_ops.py
qibotf/tests/conftest.py
qibotf/tests/__init__.py
qibotf/custom_operators/__init__.py
qibotf/custom_operators/python/__init__.py
qibotf/custom_operators/python/ops/_qibo_tf_custom_operators_cuda.so
qibotf/custom_operators/python/ops/qibo_tf_custom_operators.py
qibotf/custom_operators/python/ops/_qibo_tf_custom_operators.so
qibotf/custom_operators/python/ops/__init__.py
qibotf.libs/libcudart-72c5e614.so.11.2.152
qibotf.libs/libgomp-f7e03b3e.so.1.0.0
