Metadata-Version: 2.1
Name: qibotf
Version: 0.0.6
Summary: Simulation tools based on tensorflow.
Home-page: https://github.com/qiboteam/qibotf
Author: The Qibo team
Author-email: 
License: UNKNOWN
Platform: UNKNOWN
Classifier: Programming Language :: Python :: 3
Classifier: Topic :: Scientific/Engineering :: Physics
Requires-Python: >=3.7.0
Requires-Dist: tensorflow (==2.8.0)
Requires-Dist: qibo (>=0.1.7rc0)
